GitLiaotianRumenFix1/README.md
GitLiaotianRumenFix1/__init__.py
GitLiaotianRumenFix1/__main__.py
GitLiaotianRumenFix1/file.epub
GitLiaotianRumenFix1/index.html
GitLiaotianRumenFix1/css/__init__.py
GitLiaotianRumenFix1/css/annotations.css
GitLiaotianRumenFix1/css/main.css
GitLiaotianRumenFix1/css/normalize.css
GitLiaotianRumenFix1/css/popup.css
GitLiaotianRumenFix1/font/__init__.py
GitLiaotianRumenFix1/font/fontello.eot
GitLiaotianRumenFix1/font/fontello.svg
GitLiaotianRumenFix1/font/fontello.ttf
GitLiaotianRumenFix1/font/fontello.woff
GitLiaotianRumenFix1/img/__init__.py
GitLiaotianRumenFix1/img/annotator-glyph-sprite.png
GitLiaotianRumenFix1/img/annotator-icon-sprite.png
GitLiaotianRumenFix1/img/apple-touch-icon.png
GitLiaotianRumenFix1/img/cancelfullscreen.png
GitLiaotianRumenFix1/img/close.png
GitLiaotianRumenFix1/img/fullscreen.png
GitLiaotianRumenFix1/img/loader.gif
GitLiaotianRumenFix1/img/menu-icon.png
GitLiaotianRumenFix1/img/save.png
GitLiaotianRumenFix1/img/saved.png
GitLiaotianRumenFix1/img/settings-s.png
GitLiaotianRumenFix1/img/settings.png
GitLiaotianRumenFix1/img/star.png
GitLiaotianRumenFix1/js/__init__.py
GitLiaotianRumenFix1/js/epub.js
GitLiaotianRumenFix1/js/epub.min.js
GitLiaotianRumenFix1/js/epub.min.map
GitLiaotianRumenFix1/js/hooks.min.js
GitLiaotianRumenFix1/js/hooks.min.map
GitLiaotianRumenFix1/js/reader.js
GitLiaotianRumenFix1/js/reader.js.map
GitLiaotianRumenFix1/js/reader.min.js
GitLiaotianRumenFix1/js/reader.min.map
GitLiaotianRumenFix1/js/hooks/__init__.py
GitLiaotianRumenFix1/js/hooks/extensions/__init__.py
GitLiaotianRumenFix1/js/hooks/extensions/highlight.js
GitLiaotianRumenFix1/js/libs/__init__.py
GitLiaotianRumenFix1/js/libs/jquery.min.js
GitLiaotianRumenFix1/js/libs/localforage.min.js
GitLiaotianRumenFix1/js/libs/screenfull.js
GitLiaotianRumenFix1/js/libs/screenfull.min.js
GitLiaotianRumenFix1/js/libs/zip.min.js
GitLiaotianRumenFix1/js/plugins/__init__.py
GitLiaotianRumenFix1/js/plugins/hypothesis.js
git_liaotian_rumen_fix1-2025.3.25.0.dist-info/METADATA
git_liaotian_rumen_fix1-2025.3.25.0.dist-info/WHEEL
git_liaotian_rumen_fix1-2025.3.25.0.dist-info/entry_points.txt
git_liaotian_rumen_fix1-2025.3.25.0.dist-info/top_level.txt
git_liaotian_rumen_fix1-2025.3.25.0.dist-info/RECORD
